setup.py
dist_keras.egg-info/PKG-INFO
dist_keras.egg-info/SOURCES.txt
dist_keras.egg-info/dependency_links.txt
dist_keras.egg-info/requires.txt
dist_keras.egg-info/top_level.txt
distkeras/__init__.py
distkeras/evaluators.py
distkeras/job_deployment.py
distkeras/networking.py
distkeras/parameter_servers.py
distkeras/predictors.py
distkeras/schemes.py
distkeras/trainers.py
distkeras/transformers.py
distkeras/utils.py
distkeras/workers.py