Metadata-Version: 1.0
Name: dist-keras
Version: 0.2.0
Summary: Distributed Deep learning with Apache Spark with Keras.
Home-page: https://github.com/JoeriHermans/dist-keras
Author: Joeri Hermans
Author-email: joeri@joerihermans.com
License: GPLv3
Keywords: Keras,Deep Learning,Machine Learning,Theano,Tensorflow,Distributed,Apache Spark
Platform: UNKNOWN
